example_template_foundation/__init__.py
example_template_foundation/configuration_manager.py
example_template_foundation/logger.py
example_template_foundation/utils.py
example_template_foundation/version.py
example_template_foundation-1.0.0.dist-info/LICENSE.txt
example_template_foundation-1.0.0.dist-info/WHEEL
example_template_foundation-1.0.0.dist-info/METADATA
example_template_foundation-1.0.0.dist-info/RECORD
