Metadata-Version: 2.1
Name: example-template-foundation
Version: 1.0.0
Summary: 
License: MIT
Author: Anustup Das
Author-email: anustup@mediadistillery.com
Requires-Python: >=3.7,<4.0
Classifier: License :: OSI Approved :: MIT License
Classifier: Programming Language :: Python :: 3
Classifier: Programming Language :: Python :: 3.7
Classifier: Programming Language :: Python :: 3.8
Classifier: Programming Language :: Python :: 3.9
Requires-Dist: PyYAML (>=5.1b3)
Requires-Dist: requests (>=2.21,<3.0)
